yas3/__init__.py
yas3/aws.py
yas3/connection.py
yas3/utils.py
yas3-1.0.dist-info/LICENSE
yas3-1.0.dist-info/METADATA
yas3-1.0.dist-info/WHEEL
yas3-1.0.dist-info/top_level.txt
yas3-1.0.dist-info/RECORD
