Metadata-Version: 2.1
Name: yas3
Version: 1.0
Summary: Yet another simple S3 management tool for python.
Home-page: https://github.com/DavidMChan/yas3
Author: David Chan
Author-email: davidchan@berkeley.edu
License: Apache-2
Platform: UNKNOWN
Classifier: License :: OSI Approved :: Apache Software License
Classifier: Development Status :: 4 - Beta
Classifier: Intended Audience :: Developers
Classifier: Intended Audience :: Education
Classifier: Intended Audience :: Science/Research
Classifier: Programming Language :: Python :: 3
Classifier: Programming Language :: Python :: 3.7
Classifier: Natural Language :: English
Classifier: Operating System :: OS Independent
Classifier: Topic :: Database
Classifier: Topic :: Database :: Database Engines/Servers
Classifier: Typing :: Typed
Requires-Dist: boto3 (==1.16.9)
Requires-Dist: filetype (==1.0.7)
